mkdocs_roamlinks_plugin/__init__.py
mkdocs_roamlinks_plugin/plugin.py
tests/__init__.py
tests/test_plugin.py
mkdocs_roamlinks_plugin-0.3.2.dist-info/LICENSE
mkdocs_roamlinks_plugin-0.3.2.dist-info/METADATA
mkdocs_roamlinks_plugin-0.3.2.dist-info/WHEEL
mkdocs_roamlinks_plugin-0.3.2.dist-info/entry_points.txt
mkdocs_roamlinks_plugin-0.3.2.dist-info/top_level.txt
mkdocs_roamlinks_plugin-0.3.2.dist-info/RECORD
